pyimgbox/__init__.py
pyimgbox/_const.py
pyimgbox/_gallery.py
pyimgbox/_http.py
pyimgbox/_submission.py
pyimgbox/_utils.py
tests/test_gallery.py
tests/test_http.py
tests/test_submission.py
tests/test_utils.py
pyimgbox-1.0.7.dist-info/LICENSE
pyimgbox-1.0.7.dist-info/METADATA
pyimgbox-1.0.7.dist-info/WHEEL
pyimgbox-1.0.7.dist-info/top_level.txt
pyimgbox-1.0.7.dist-info/RECORD
