Metadata-Version: 2.1
Name: pyimgbox
Version: 1.0.7
Summary: API for uploading images to imgbox.com
Author-email: plotski <plotski@example.org>
License: GPL-3.0-or-later
Project-URL: Repository, https://codeberg.org/plotski/pyimgbox
Project-URL: Bug Tracker, https://codeberg.org/plotski/pyimgbox/issues
Project-URL: Changelog, https://codeberg.org/plotski/pyimgbox/raw/branch/master/NEWS
Classifier: Programming Language :: Python :: 3
Classifier: License :: OSI Approved :: GNU General Public License v3 or later (GPLv3+)
Classifier: Operating System :: OS Independent
Classifier: Topic :: Software Development :: Libraries
Classifier: Intended Audience :: Developers
Requires-Python: >=3.8
License-File: LICENSE
Requires-Dist: httpx==0.*
Requires-Dist: beautifulsoup4
Provides-Extra: dev
Requires-Dist: pytest; extra == "dev"
Requires-Dist: pytest-asyncio; extra == "dev"
Requires-Dist: pytest-mock; extra == "dev"
Requires-Dist: pytest-httpserver; extra == "dev"
Requires-Dist: tox; extra == "dev"
Requires-Dist: coverage; extra == "dev"
Requires-Dist: pytest-cov; extra == "dev"
Requires-Dist: ruff; extra == "dev"
Requires-Dist: flake8; extra == "dev"
Requires-Dist: isort; extra == "dev"
